{"code":200.0,"message":"OK","body":{"result_notifications":[],"command":{"exclude_subways":[],"passing_stations":[{"station_id":"SES42M193","departure_time":"08:00:00"},{"station_id":"SES2547"}],"day_type":"WEEKDAY","result_time_format":"TIME_STRING","finding_type":"NORMAL","walking_speed":4.5,"region":"METROPOLITAN"},"finding_type":"NORMAL","day_type":"WEEKDAY","routes":{"shortest_time":{"fare":2150.0,"time_required":4640.0,"departure_time":"08:08:30","arrival_time":"09:25:50","sections":[{"train_type":"GENERAL","line_id":"SES42","line_name":"서해선","transfer_type":"NONE","transfer_seconds":0.0,"boarding":{"dest_station_id":"SES42M282","dest_station_name":"대곡","fast_transfer_doors":["4-4"]},"alighting":{"fast_alighting_doors":["2-3"],"door_direction":"LEFT"},"nodes":[{"station_id":"SES42M193","station_name":"시흥대야","wcong_x":454208.0,"wcong_y":1097465.0,"x":454208.0,"y":1097465.0,"arrival_time":"08:08:00","departure_time":"08:08:30"},{"station_id":"SES42M192","station_name":"소새울","wcong_x":455168.0,"wcong_y":1102571.0,"x":455168.0,"y":1102571.0,"arrival_time":"08:11:00","departure_time":"08:11:30"},{"station_id":"SES42M191","station_name":"소사","wcong_x":454685.0,"wcong_y":1106567.0,"x":454685.0,"y":1106567.0,"arrival_time":"08:14:30","departure_time":"08:15:00"}],"first_train":false,"last_train":false},{"train_type":"GENERAL","line_id":"SES1","line_name":"1호선","transfer_type":"NORMAL","transfer_seconds":240.0,"boarding":{"dest_station_id":"SES1910","dest_station_name":"양주","fast_transfer_doors":["10-4"]},"alighting":{"fast_alighting_doors":["1-1","10-4"],"door_direction":"RIGHT"},"nodes":[{"station_id":"SES1814","station_name":"소사","wcong_x":454814.0,"wcong_y":1106537.0,"x":454814.0,"y":1106537.0,"arrival_time":"08:20:00","departure_time":"08:20:30"},{"station_id":"SES1803","station_name":"역곡","wcong_x":458445.0,"wcong_y":1107227.0,"x":458445.0,"y":1107227.0,"arrival_time":"08:22:30","departure_time":"08:23:00"},{"station_id":"SES1821","station_name":"온수","wcong_x":461051.0,"wcong_y":1109188.0,"x":461051.0,"y":1109188.0,"arrival_time":"08:24:30","departure_time":"08:25:00"},{"station_id":"SES1802","station_name":"오류동","wcong_x":465690.0,"wcong_y":1109734.0,"x":465690.0,"y":1109734.0,"arrival_time":"08:27:30","departure_time":"08:28:00"},{"station_id":"SES1801","station_name":"개봉","wcong_x":468765.0,"wcong_y":1109797.0,"x":468765.0,"y":1109797.0,"arrival_time":"08:30:00","departure_time":"08:30:30"},{"station_id":"SES1813","station_name":"구일","wcong_x":471192.0,"wcong_y":1110241.0,"x":471192.0,"y":1110241.0,"arrival_time":"08:32:00","departure_time":"08:32:30"},{"station_id":"SES1701","station_name":"구로","wcong_x":473984.0,"wcong_y":1112204.0,"x":473984.0,"y":1112204.0,"arrival_time":"08:34:30","departure_time":"08:35:30"},{"station_id":"SES1007","station_name":"신도림","wcong_x":475976.0,"wcong_y":1113746.0,"x":475976.0,"y":1113746.0,"arrival_time":"08:37:30","departure_time":"08:38:00"},{"station_id":"SES1006","station_name":"영등포","wcong_x":479567.0,"wcong_y":1115619.0,"x":479567.0,"y":1115619.0,"arrival_time":"08:40:00","departure_time":"08:40:30"},{"station_id":"SES1032","station_name":"신길","wcong_x":481958.0,"wcong_y":1115926.0,"x":481958.0,"y":1115926.0,"arrival_time":"08:42:30","departure_time":"08:43:00"},{"station_id":"SES1005","station_name":"대방","wcong_x":483754.0,"wcong_y":1114972.0,"x":483754.0,"y":1114972.0,"arrival_time":"08:44:00","departure_time":"08:44:30"},{"station_id":"SES1004","station_name":"노량진","wcong_x":487205.0,"wcong_y":1115164.0,"x":487205.0,"y":1115164.0,"arrival_time":"08:46:30","departure_time":"08:47:00"},{"station_id":"SES1003","station_name":"용산","wcong_x":492184.0,"wcong_y":1119523.0,"x":492184.0,"y":1119523.0,"arrival_time":"08:50:00","departure_time":"08:50:30"},{"station_id":"SES1002","station_name":"남영","wcong_x":493666.0,"wcong_y":1122517.0,"x":493666.0,"y":1122517.0,"arrival_time":"08:52:30","departure_time":"08:53:00"},{"station_id":"SES0150","station_name":"서울역","wcong_x":493835.0,"wcong_y":1126794.0,"x":493835.0,"y":1126794.0,"arrival_time":"08:55:30","departure_time":"08:56:00"}],"first_train":false,"last_train":false},{"train_type":"GENERAL","line_id":"SES4","line_name":"4호선","transfer_type":"NORMAL","transfer_seconds":180.0,"boarding":{"dest_station_id":"SES0409","dest_station_name":"불암산","fast_transfer_doors":["1-1","1-2"]},"alighting":{"fast_alighting_doors":["1-1","9-2"],"door_direction":"LEFT"},"nodes":[{"station_id":"SES0426","station_name":"서울역","wcong_x":493957.0,"wcong_y":1125975.0,"x":493957.0,"y":1125975.0,"arrival_time":"08:58:00","departure_time":"08:58:30"},{"station_id":"SES0425","station_name":"회현","wcong_x":495237.0,"wcong_y":1127565.0,"x":495237.0,"y":1127565.0,"arrival_time":"09:00:00","departure_time":"09:00:30"},{"station_id":"SES0424","station_name":"명동","wcong_x":496996.0,"wcong_y":1128176.0,"x":496996.0,"y":1128176.0,"arrival_time":"09:01:30","departure_time":"09:02:00"},{"station_id":"SES0423","station_name":"충무로","wcong_x":498952.0,"wcong_y":1128328.0,"x":498952.0,"y":1128328.0,"arrival_time":"09:03:00","departure_time":"09:03:30"},{"station_id":"SES0422","station_name":"동대문역사문화공원","wcong_x":501700.0,"wcong_y":1129305.0,"x":501700.0,"y":1129305.0,"arrival_time":"09:05:30","departure_time":"09:06:00"}],"first_train":false,"last_train":false},{"train_type":"GENERAL","line_id":"SES2","line_name":"2호선","transfer_type":"NORMAL","transfer_seconds":60.0,"boarding":{"dest_station_id":"SES0211","dest_station_name":"성수","fast_transfer_doors":["6-1"]},"alighting":{"fast_alighting_doors":["2-3","9-2"],"door_direction":"RIGHT"},"nodes":[{"station_id":"SES0205","station_name":"동대문역사문화공원","wcong_x":501989.0,"wcong_y":1129480.0,"x":501989.0,"y":1129480.0,"arrival_time":"09:05:30","departure_time":"09:06:30"},{"station_id":"SES0206","station_name":"신당","wcong_x":504302.0,"wcong_y":1129483.0,"x":504302.0,"y":1129483.0,"arrival_time":"09:08:00","departure_time":"09:08:30"},{"station_id":"SES0207","station_name":"상왕십리","wcong_x":506466.0,"wcong_y":1129141.0,"x":506466.0,"y":1129141.0,"arrival_time":"09:09:30","departure_time":"09:10:00"},{"station_id":"SES0208","station_name":"왕십리","wcong_x":508195.0,"wcong_y":1128262.0,"x":508195.0,"y":1128262.0,"arrival_time":"09:11:00","departure_time":"09:12:00"}],"first_train":false,"last_train":false},{"train_type":"GENERAL","line_id":"SES5","line_name":"5호선","transfer_type":"NORMAL","transfer_seconds":180.0,"boarding":{"dest_station_id":"SES2561","dest_station_name":"마천","fast_transfer_doors":[]},"alighting":{"fast_alighting_doors":["3-3"],"door_direction":"RIGHT"},"nodes":[{"station_id":"SES2541","station_name":"왕십리","wcong_x":508246.0,"wcong_y":1128476.0,"x":508246.0,"y":1128476.0,"arrival_time":"09:13:30","departure_time":"09:14:00"},{"station_id":"SES2542","station_name":"마장","wcong_x":509494.0,"wcong_y":1129614.0,"x":509494.0,"y":1129614.0,"arrival_time":"09:15:00","departure_time":"09:15:20"},{"station_id":"SES2543","station_name":"답십리","wcong_x":511609.0,"wcong_y":1129847.0,"x":511609.0,"y":1129847.0,"arrival_time":"09:17:00","departure_time":"09:17:30"},{"station_id":"SES2544","station_name":"장한평","wcong_x":514071.0,"wcong_y":1128358.0,"x":514071.0,"y":1128358.0,"arrival_time":"09:19:10","departure_time":"09:19:40"},{"station_id":"SES2545","station_name":"군자","wcong_x":517564.0,"wcong_y":1127125.0,"x":517564.0,"y":1127125.0,"arrival_time":"09:21:20","departure_time":"09:22:00"},{"station_id":"SES2546","station_name":"아차산","wcong_x":519786.0,"wcong_y":1125767.0,"x":519786.0,"y":1125767.0,"arrival_time":"09:23:30","departure_time":"09:24:00"},{"station_id":"SES2547","station_name":"광나루","wcong_x":522871.0,"wcong_y":1123842.0,"x":522871.0,"y":1123842.0,"arrival_time":"09:25:50","departure_time":"09:26:20"}],"first_train":false,"last_train":false}]},"min_transfer":{"fare":2150.0,"time_required":5660.0,"departure_time":"08:08:30","arrival_time":"09:42:50","sections":[{"train_type":"GENERAL","line_id":"SES42","line_name":"서해선","transfer_type":"NONE","transfer_seconds":0.0,"boarding":{"dest_station_id":"SES42M282","dest_station_name":"대곡","fast_transfer_doors":["3-3","4-4"]},"alighting":{"fast_alighting_doors":["3-3","4-4"],"door_direction":"LEFT"},"nodes":[{"station_id":"SES42M193","station_name":"시흥대야","wcong_x":454208.0,"wcong_y":1097465.0,"x":454208.0,"y":1097465.0,"arrival_time":"08:08:00","departure_time":"08:08:30"},{"station_id":"SES42M192","station_name":"소새울","wcong_x":455168.0,"wcong_y":1102571.0,"x":455168.0,"y":1102571.0,"arrival_time":"08:11:00","departure_time":"08:11:30"},{"station_id":"SES42M191","station_name":"소사","wcong_x":454685.0,"wcong_y":1106567.0,"x":454685.0,"y":1106567.0,"arrival_time":"08:14:30","departure_time":"08:15:00"},{"station_id":"SES42M278","station_name":"부천종합운동장","wcong_x":455261.0,"wcong_y":1113016.0,"x":455261.0,"y":1113016.0,"arrival_time":"08:18:00","departure_time":"08:18:30"},{"station_id":"SES42M279","station_name":"원종","wcong_x":456872.0,"wcong_y":1118017.0,"x":456872.0,"y":1118017.0,"arrival_time":"08:21:00","departure_time":"08:21:30"},{"station_id":"SES42M280","station_name":"김포공항","wcong_x":456741.0,"wcong_y":1128452.0,"x":456741.0,"y":1128452.0,"arrival_time":"08:26:00","departure_time":"08:26:30"}],"first_train":false,"last_train":false},{"train_type":"GENERAL","line_id":"SES5","line_name":"5호선","transfer_type":"NORMAL","transfer_seconds":540.0,"boarding":{"dest_station_id":"SES5M245","dest_station_name":"하남검단산","fast_transfer_doors":[]},"alighting":{"fast_alighting_doors":["3-3"],"door_direction":"RIGHT"},"nodes":[{"station_id":"SES2513","station_name":"김포공항","wcong_x":456101.0,"wcong_y":1128537.0,"x":456101.0,"y":1128537.0,"arrival_time":"08:34:40","departure_time":"08:35:10"},{"station_id":"SES2514","station_name":"송정","wcong_x":458569.0,"wcong_y":1128272.0,"x":458569.0,"y":1128272.0,"arrival_time":"08:37:20","departure_time":"08:37:50"},{"station_id":"SES2515","station_name":"마곡","wcong_x":461278.0,"wcong_y":1128008.0,"x":461278.0,"y":1128008.0,"arrival_time":"08:39:20","departure_time":"08:39:40"},{"station_id":"SES2516","station_name":"발산","wcong_x":464158.0,"wcong_y":1127573.0,"x":464158.0,"y":1127573.0,"arrival_time":"08:41:20","departure_time":"08:41:50"},{"station_id":"SES2517","station_name":"우장산","wcong_x":463841.0,"wcong_y":1124837.0,"x":463841.0,"y":1124837.0,"arrival_time":"08:43:20","departure_time":"08:43:50"},{"station_id":"SES2518","station_name":"화곡","wcong_x":464750.0,"wcong_y":1122847.0,"x":464750.0,"y":1122847.0,"arrival_time":"08:45:20","departure_time":"08:45:50"},{"station_id":"SES2519","station_name":"까치산","wcong_x":466069.0,"wcong_y":1120231.0,"x":466069.0,"y":1120231.0,"arrival_time":"08:47:20","departure_time":"08:48:00"},{"station_id":"SES2520","station_name":"신정","wcong_x":468199.0,"wcong_y":1118229.0,"x":468199.0,"y":1118229.0,"arrival_time":"08:49:50","departure_time":"08:50:30"},{"station_id":"SES2521","station_name":"목동","wcong_x":470084.0,"wcong_y":1118533.0,"x":470084.0,"y":1118533.0,"arrival_time":"08:51:40","departure_time":"08:52:20"},{"station_id":"SES2522","station_name":"오목교","wcong_x":472444.0,"wcong_y":1118086.0,"x":472444.0,"y":1118086.0,"arrival_time":"08:53:40","departure_time":"08:54:10"},{"station_id":"SES2523","station_name":"양평","wcong_x":474900.0,"wcong_y":1118373.0,"x":474900.0,"y":1118373.0,"arrival_time":"08:55:30","departure_time":"08:56:00"},{"station_id":"SES2524","station_name":"영등포구청","wcong_x":476867.0,"wcong_y":1117996.0,"x":476867.0,"y":1117996.0,"arrival_time":"08:57:10","departure_time":"08:57:50"},{"station_id":"SES2525","station_name":"영등포시장","wcong_x":479045.0,"wcong_y":1117572.0,"x":479045.0,"y":1117572.0,"arrival_time":"08:59:00","departure_time":"08:59:30"},{"station_id":"SES2526","station_name":"신길","wcong_x":481195.0,"wcong_y":1116170.0,"x":481195.0,"y":1116170.0,"arrival_time":"09:01:00","departure_time":"09:01:30"},{"station_id":"SES2527","station_name":"여의도","wcong_x":483292.0,"wcong_y":1117309.0,"x":483292.0,"y":1117309.0,"arrival_time":"09:03:00","departure_time":"09:03:40"},{"station_id":"SES2528","station_name":"여의나루","wcong_x":485191.0,"wcong_y":1118798.0,"x":485191.0,"y":1118798.0,"arrival_time":"09:05:00","departure_time":"09:05:40"},{"station_id":"SES2529","station_name":"마포","wcong_x":488039.0,"wcong_y":1122239.0,"x":488039.0,"y":1122239.0,"arrival_time":"09:07:40","departure_time":"09:08:10"},{"station_id":"SES2530","station_name":"공덕","wcong_x":489274.0,"wcong_y":1123622.0,"x":489274.0,"y":1123622.0,"arrival_time":"09:09:20","departure_time":"09:10:10"},{"station_id":"SES2531","station_name":"애오개","wcong_x":490428.0,"wcong_y":1126083.0,"x":490428.0,"y":1126083.0,"arrival_time":"09:11:30","departure_time":"09:12:00"},{"station_id":"SES2532","station_name":"충정로","wcong_x":491836.0,"wcong_y":1128029.0,"x":491836.0,"y":1128029.0,"arrival_time":"09:13:20","departure_time":"09:13:50"},{"station_id":"SES2533","station_name":"서대문","wcong_x":492631.0,"wcong_y":1129506.0,"x":492631.0,"y":1129506.0,"arrival_time":"09:14:50","departure_time":"09:15:30"},{"station_id":"SES2534","station_name":"광화문","wcong_x":494793.0,"wcong_y":1131141.0,"x":494793.0,"y":1131141.0,"arrival_time":"09:17:00","departure_time":"09:17:30"},{"station_id":"SES2535","station_name":"종로3가","wcong_x":497884.0,"wcong_y":1131402.0,"x":497884.0,"y":1131402.0,"arrival_time":"09:19:10","departure_time":"09:19:40"},{"station_id":"SES2536","station_name":"을지로4가","wcong_x":499568.0,"wcong_y":1130007.0,"x":499568.0,"y":1130007.0,"arrival_time":"09:21:20","departure_time":"09:21:50"},{"station_id":"SES2537","station_name":"동대문역사문화공원","wcong_x":501279.0,"wcong_y":1129191.0,"x":501279.0,"y":1129191.0,"arrival_time":"09:23:20","departure_time":"09:24:00"},{"station_id":"SES2538","station_name":"청구","wcong_x":503080.0,"wcong_y":1127967.0,"x":503080.0,"y":1127967.0,"arrival_time":"09:25:20","departure_time":"09:25:50"},{"station_id":"SES2539","station_name":"신금호","wcong_x":504527.0,"wcong_y":1126376.0,"x":504527.0,"y":1126376.0,"arrival_time":"09:27:20","departure_time":"09:27:40"},{"station_id":"SES2540","station_name":"행당","wcong_x":506519.0,"wcong_y":1127178.0,"x":506519.0,"y":1127178.0,"arrival_time":"09:29:00","departure_time":"09:29:20"},{"station_id":"SES2541","station_name":"왕십리","wcong_x":508246.0,"wcong_y":1128476.0,"x":508246.0,"y":1128476.0,"arrival_time":"09:30:30","departure_time":"09:31:00"},{"station_id":"SES2542","station_name":"마장","wcong_x":509494.0,"wcong_y":1129614.0,"x":509494.0,"y":1129614.0,"arrival_time":"09:32:00","departure_time":"09:32:20"},{"station_id":"SES2543","station_name":"답십리","wcong_x":511609.0,"wcong_y":1129847.0,"x":511609.0,"y":1129847.0,"arrival_time":"09:34:00","departure_time":"09:34:30"},{"station_id":"SES2544","station_name":"장한평","wcong_x":514071.0,"wcong_y":1128358.0,"x":514071.0,"y":1128358.0,"arrival_time":"09:36:10","departure_time":"09:36:40"},{"station_id":"SES2545","station_name":"군자","wcong_x":517564.0,"wcong_y":1127125.0,"x":517564.0,"y":1127125.0,"arrival_time":"09:38:20","departure_time":"09:39:00"},{"station_id":"SES2546","station_name":"아차산","wcong_x":519786.0,"wcong_y":1125767.0,"x":519786.0,"y":1125767.0,"arrival_time":"09:40:30","departure_time":"09:41:00"},{"station_id":"SES2547","station_name":"광나루","wcong_x":522871.0,"wcong_y":1123842.0,"x":522871.0,"y":1123842.0,"arrival_time":"09:42:50","departure_time":"09:43:20"}],"first_train":false,"last_train":false}]}}}}